DJ003/__init__.py
DJ003/run.py
dj003-0.1.2.dist-info/entry_points.txt
dj003-0.1.2.dist-info/WHEEL
dj003-0.1.2.dist-info/METADATA
dj003-0.1.2.dist-info/RECORD
