Metadata-Version: 2.1
Name: dj003
Version: 0.1.2
Summary: This is a django project
License: Apache 2.0
Author: xiaodeng
Author-email: xiaodengteacher@qq.com
Requires-Python: >=3.7,<4.0
Classifier: License :: Other/Proprietary License
Classifier: Programming Language :: Python :: 3
Classifier: Programming Language :: Python :: 3.7
Classifier: Programming Language :: Python :: 3.8
Classifier: Programming Language :: Python :: 3.9
Provides-Extra: pyopenxl
Requires-Dist: Django (>=3.2.6,<4.0.0)
Requires-Dist: selenium (>=3,<4); extra == "pyopenxl"
